Workbook
Name Slicer_Discount_Bucket: #N/A
Name Slicer_Gender: #N/A
Name Slicer_Region: #N/A
Name Slicer_Sales_Channel: #N/A
Name Slicer_Year: #N/A

Sheet Cleaned_Data
A1: Order_ID | B1: Gender | C1: Product_Line | D1: Product_Name | E1: Size | F1: Units_Sold | G1: MRP | H1: Discount | I1: Selling_Price | J1: Revenue | K1: Order_Date | L1: Sales_Channel | M1: Region | N1: Profit | O1: Discount_Bucket | P1: Year | Q1: Profit_Margin
A2: 2001 | B2: Women | C2: Soccer | D2: Tiempo Legend | E2: M | F2: 3 | G2: 5234.155 | H2: 0 | I2: 5233.155 | J2: 15699.465 | K2: 45482 | L2: Retail | M2: Hyderabad | N2: -112.53 | O2: 0-10% | P2: 2024 | Q2: =IF(Nike_Sales_Cleaned[[#This Row],[Revenue]] = 0, 0, Nike_Sales_Cleaned[[#This Row],[Profit]]/Nike_Sales_Cleaned[[#This Row],[Revenue]]) -> -0.0071677602
A3: 2010 | B3: Kids | C3: Lifestyle | D3: Waffle One | E3: L | F3: 1 | G3: 6216.29 | H3: 0 | I3: 6215.29 | J3: 6215.29 | K3: 45673 | L3: Online | M3: Pune | N3: 1965.56 | O3: 0-10% | P3: 2025 | Q3: =IF(Nike_Sales_Cleaned[[#This Row],[Revenue]] = 0, 0, Nike_Sales_Cleaned[[#This Row],[Profit]]/Nike_Sales_Cleaned[[#This Row],[Revenue]]) -> 0.3162459
A4: 2048 | B4: Men | C4: Lifestyle | D4: Waffle One | E4: M | F4: 3 | G4: 6216.29 | H4: 0.94 | I4: 6216.23 | J4: 18648.69 | K4: 45549 | L4: Online | M4: Mumbai | N4: -642.02 | O4: 50%+ | P4: 2024 | Q4: =IF(Nike_Sales_Cleaned[[#This Row],[Revenue]] = 0, 0, Nike_Sales_Cleaned[[#This Row],[Profit]]/Nike_Sales_Cleaned[[#This Row],[Revenue]]) -> -0.034427083
A5: 2060 | B5: Men | C5: Lifestyle | D5: Waffle One | E5: L | F5: 2 | G5: 6216.29 | H5: 0 | I5: 6215.29 | J5: 12430.58 | K5: 45484 | L5: Online | M5: Bengaluru | N5: 2821.59 | O5: 0-10% | P5: 2024 | Q5: =IF(Nike_Sales_Cleaned[[#This Row],[Revenue]] = 0, 0, Nike_Sales_Cleaned[[#This Row],[Profit]]/Nike_Sales_Cleaned[[#This Row],[Revenue]]) -> 0.2269878
A6: 2017 | B6: Women | C6: Basketball | D6: Air Jordan | E6: 9 | F6: 4 | G6: 5981.92 | H6: 0 | I6: 5980.92 | J6: 23923.68 | K6: 45733 | L6: Retail | M6: Delhi | N6: 1946.24 | O6: 0-10% | P6: 2025 | Q6: =IF(Nike_Sales_Cleaned[[#This Row],[Revenue]] = 0, 0, Nike_Sales_Cleaned[[#This Row],[Profit]]/Nike_Sales_Cleaned[[#This Row],[Revenue]]) -> 0.081352033
A7: 2063 | B7: Women | C7: Basketball | D7: Air Jordan | E7: M | F7: 1 | G7: 5981.92 | H7: 0.16 | I7: 5981.08 | J7: 5981.08 | K7: 45541 | L7: Retail | M7: Pune | N7: 1130.31 | O7: 10%-20% | P7: 2024 | Q7: =IF(Nike_Sales_Cleaned[[#This Row],[Revenue]] = 0, 0, Nike_Sales_Cleaned[[#This Row],[Profit]]/Nike_Sales_Cleaned[[#This Row],[Revenue]]) -> 0.18898092
A8: 2075 | B8: Kids | C8: Basketball | D8: Air Jordan | E8: L | F8: 4 | G8: 5981.92 | H8: 0 | I8: 5980.92 | J8: 23923.68 | K8: 45852 | L8: Online | M8: Pune | N8: 2345.35 | O8: 0-10% | P8: 2025 | Q8: =IF(Nike_Sales_Cleaned[[#This Row],[Revenue]] = 0, 0, Nike_Sales_Cleaned[[#This Row],[Profit]]/Nike_Sales_Cleaned[[#This Row],[Revenue]]) -> 0.098034667
A9: 2026 | B9: Kids | C9: Lifestyle | D9: Blazer Mid | E9: XL | F9: 1 | G9: 4904.79 | H9: 0.16 | I9: 4903.95 | J9: 4903.95 | K9: 45514 | L9: Retail | M9: Kolkata | N9: 2301.64 | O9: 10%-20% | P9: 2024 | Q9: =IF(Nike_Sales_Cleaned[[#This Row],[Revenue]] = 0, 0, Nike_Sales_Cleaned[[#This Row],[Profit]]/Nike_Sales_Cleaned[[#This Row],[Revenue]]) -> 0.4693441
A10: 2071 | B10: Kids | C10: Lifestyle | D10: Blazer Mid | E10: M | F10: 3 | G10: 4904.79 | H10: 0.49 | I10: 4904.28 | J10: 14712.84 | K10: 45669 | L10: Retail | M10: Pune | N10: -882.96 | O10: 30%-50% | P10: 2025 | Q10: =IF(Nike_Sales_Cleaned[[#This Row],[Revenue]] = 0, 0, Nike_Sales_Cleaned[[#This Row],[Profit]]/Nike_Sales_Cleaned[[#This Row],[Revenue]]) -> -0.060012887
A11: 2073 | B11: Women | C11: Lifestyle | D11: Blazer Mid | E11: 12 | F11: 4 | G11: 4904.79 | H11: 0.85 | I11: 4904.64 | J11: 19618.56 | K11: 45599 | L11: Online | M11: Hyderabad | N11: 443.86 | O11: 50%+ | P11: 2024 | Q11: =IF(Nike_Sales_Cleaned[[#This Row],[Revenue]] = 0, 0, Nike_Sales_Cleaned[[#This Row],[Profit]]/Nike_Sales_Cleaned[[#This Row],[Revenue]]) -> 0.022624494
A12: 2002 | B12: Women | C12: Basketball | D12: Zoom Freak | E12: XL | F12: 3 | G12: 7845.46 | H12: 0 | I12: 7844.46 | J12: 23533.38 | K12: 45723 | L12: Retail | M12: Delhi | N12: 145.08 | O12: 0-10% | P12: 2025 | Q12: =IF(Nike_Sales_Cleaned[[#This Row],[Revenue]] = 0, 0, Nike_Sales_Cleaned[[#This Row],[Profit]]/Nike_Sales_Cleaned[[#This Row],[Revenue]]) -> 0.0061648603
A13: 2047 | B13: Women | C13: Training | D13: SuperRep Go | E13: 10 | F13: 1 | G13: 5873.83 | H13: 0 | I13: 5872.83 | J13: 5872.83 | K13: 45456 | L13: Retail | M13: Bengaluru | N13: 2888.68 | O13: 0-10% | P13: 2024 | Q13: =IF(Nike_Sales_Cleaned[[#This Row],[Revenue]] = 0, 0, Nike_Sales_Cleaned[[#This Row],[Profit]]/Nike_Sales_Cleaned[[#This Row],[Revenue]]) -> 0.49187189
... A483: 4495 | B483: Kids | C483: Basketball | D483: Kyrie Flytrap | E483: XL | F483: 3 | G483: 5117.865 | H483: 0 | I483: 5116.865 | J483: 15350.595 | K483: 45791 | L483: Online | M483: Pune | N483: 2.97 | O483: 0-10% | P483: 2025 | Q483: =IF(Nike_Sales_Cleaned[[#This Row],[Revenue]] = 0, 0, Nike_Sales_Cleaned[[#This Row],[Profit]]/Nike_Sales_Cleaned[[#This Row],[Revenue]]) -> 0.00019347784

Sheet Analysis
B1: KPI
B6: Sum of MRP | C6: Sum of Revenue | D6: Sum of Profit | E6: Average of Profit_Margin | F6: Sum of Units_Sold
B7: 2929776 | C7: 7382043.9 | D7: 665885.02 | E7: 0.12218396 | F7: 1213
B10: Pivot Tables and Analysis
B15: City | C15: Revenue | D15: Profit
B16: Mumbai | C16: 1496104.1 | D16: 147349.83
B17: Pune | C17: 1350020.4 | D17: 102767.3
B18: Kolkata | C18: 1170688.1 | D18: 105297.25
B19: Bengaluru | C19: 1160775.7 | D19: 105648.19
B20: Hyderabad | C20: 1112206.1 | D20: 107847.96
B21: Delhi | C21: 1092249.5 | D21: 96974.49
B22: Grand Total | C22: 7382043.9 | D22: 665885.02
B34: Months | C34: Revenue | D34: Profit | P34: Dicount | Q34: Revenue | R34: Profit Margin
B35: Jan | C35: 675913.71 | D35: 48539.31 | P35: 0-10% | Q35: 5365051.8 | R35: 0.09030209
B36: Feb | C36: 523293.67 | D36: 52580.6 | P36: 10%-20% | Q36: 206515.8 | R36: 0.14054847
B37: Mar | C37: 621844.63 | D37: 57165.23 | P37: 20%-30% | Q37: 308889.27 | R37: 0.10431622
B38: Apr | C38: 534609.54 | D38: 47384.71 | P38: 30%-50% | Q38: 528419.09 | R38: 0.11038456
B39: May | C39: 667950.21 | D39: 53019.5 | P39: 50%+ | Q39: 973167.98 | R39: 0.06353752
B40: Jun | C40: 708241.89 | D40: 65613.46 | P40: Grand Total | Q40: 7382043.9 | R40: 0.09020334
B41: Jul | C41: 616093.77 | D41: 44002.22
B42: Aug | C42: 481893.43 | D42: 45502.94
B43: Sep | C43: 604394.58 | D43: 58926.12
B44: Oct | C44: 670723.49 | D44: 61830.71
B45: Nov | C45: 735811.3 | D45: 73500.67
B46: Dec | C46: 541273.71 | D46: 57819.55 | W46: Gender | X46: Profit
B47: Grand Total | C47: 7382043.9 | D47: 665885.02 | W47: Kids | X47: 0.37811962 | AB47: Region | AC47: Profit Margin
W48: Men | X48: 0.31515713 | AB48: Mumbai | AC48: 0.098489024
W49: Women | X49: 0.30672325 | AB49: Hyderabad | AC49: 0.096967602
W50: Grand Total | X50: 1 | AB50: Bengaluru | AC50: 0.091015163
AB51: Kolkata | AC51: 0.089944753
H52: Row Labels | I52: Profit Margin | K52: Product_Line | L52: Revenue | M52: Profit Margin | AB52: Delhi | AC52: 0.08878419
H53: Premier III | I53: 0.14645418 | K53: Soccer | L53: 0.19836066 | M53: 0.11173716 | AB53: Pune | AC53: 0.076122774
H54: Blazer Mid | I54: 0.13163694 | K54: Running | L54: 0.16476402 | M54: 0.10794174 | AB54: Grand Total | AC54: 0.09020334
H55: Air Zoom | I55: 0.12192411 | K55: Training | L55: 0.22669475 | M55: 0.082145329
H56: Free RN | I56: 0.12128826 | K56: Lifestyle | L56: 0.20841671 | M56: 0.079617713
H57: Pegasus Turbo | I57: 0.10865472 | K57: Basketball | L57: 0.20176387 | M57: 0.074535608
H58: Grand Total | I58: 0.12861759 | K58: Grand Total | L58: 1 | M58: 0.09020334

Sheet Calculations
B3: MRP | C3: =GETPIVOTDATA("Sum of MRP",Analysis!$B$6) -> 2929776 | F3: Top Product | G3: =Analysis!H53 -> Premier III
B4: PROFIT | C4: =GETPIVOTDATA("Sum of Profit",Analysis!$B$6) -> 665885.02 | F4: Best Segment | G4: =Analysis!K53 -> Soccer
B5: REVENUE | C5: =GETPIVOTDATA("Sum of Revenue",Analysis!$B$6) -> 7382043.9
B8: Profit Margin | C8: =C4/C5 -> 0.09020334
B9: Units Sold | C9: =GETPIVOTDATA("Sum of Units_Sold",Analysis!$B$6) -> 1213

Sheet Dashboard
AC14: Revenue and Profit over product line
AC15: Product_Line | AD15: Revenue | AE15: Profit Margin
AC16: Soccer | AD16: 0.19836066 | AE16: 0.11173716
AC17: Running | AD17: 0.16476402 | AE17: 0.10794174
AC18: Training | AD18: 0.22669475 | AE18: 0.082145329
AC19: Lifestyle | AD19: 0.20841671 | AE19: 0.079617713
AC20: Basketball | AD20: 0.20176387 | AE20: 0.074535608
D54: KEY INSIGHTS AND RECOMMENDATIONS
D56: Channel Performance: Retail channel consistently delivers higher profit margins compared to Online sales. | T56: Recommendation: Focus on strengthening retail presence while optimizing online discount strategies to improve margins.
D58: Discount Strategy Impact: High discount ranges (>50%) significantly reduce profitability (~6%), despite contributing to revenue. | T58: Recommendation: Limit deep discounting and prioritize moderate discount bands (10–30%) for better profit efficiency.
D60: Customer Segment Insight: Kids category contributes the highest share of profit (~38%), making it a key growth driver. | T60: Recommendation: Increase focus on high-performing segments through targeted marketing and inventory allocation.
D62: Regional Performance: Certain regions generate high revenue but relatively lower profitability. | T62: Recommendation: Investigate cost structure and pricing strategy in underperforming regions.
